README.rst
setup.cfg
setup.py
monitoring/__init__.py
monitoring/http.py
pymonitoring.egg-info/PKG-INFO
pymonitoring.egg-info/SOURCES.txt
pymonitoring.egg-info/dependency_links.txt
pymonitoring.egg-info/not-zip-safe
pymonitoring.egg-info/top_level.txt