Metadata-Version: 1.0
Name: pymonitoring
Version: 0.1.0
Summary: Injectable HTTP monitoring interface.
Home-page: https://github.com/povilasb/pymonitoring
Author: Povilas Balciunas
Author-email: balciunas90@gmail.com
License: MIT
Platform: UNKNOWN
